langevals_ragas/bleu_score.py
langevals_ragas/context_f1.py
langevals_ragas/context_precision.py
langevals_ragas/context_recall.py
langevals_ragas/factual_correctness.py
langevals_ragas/faithfulness.py
langevals_ragas/lib/common.py
langevals_ragas/lib/model_to_langchain.py
langevals_ragas/response_context_precision.py
langevals_ragas/response_context_recall.py
langevals_ragas/response_relevancy.py
langevals_ragas/rouge_score.py
langevals_ragas/rubrics_based_scoring.py
langevals_ragas/sql_query_equivalence.py
langevals_ragas/summarization_score.py
langevals_ragas-0.1.14.dist-info/METADATA
langevals_ragas-0.1.14.dist-info/WHEEL
langevals_ragas-0.1.14.dist-info/RECORD
