Metadata-Version: 2.4
Name: langevals-ragas
Version: 0.1.14
Summary: LangEvals Ragas evaluator
License: MIT
Author: Rogerio Chaves
Author-email: rogerio@langwatch.ai
Requires-Python: >=3.11,<4.0
Classifier: License :: OSI Approved :: MIT License
Classifier: Programming Language :: Python :: 3
Classifier: Programming Language :: Python :: 3.11
Classifier: Programming Language :: Python :: 3.12
Classifier: Programming Language :: Python :: 3.13
Classifier: Programming Language :: Python :: 3.14
Requires-Dist: langchain-openai (>=0.1.23)
Requires-Dist: langchain_community (>=0.2.16)
Requires-Dist: langevals-core (>=0.1.18,<0.2.0)
Requires-Dist: litellm (==1.76.0)
Requires-Dist: ragas (==0.2.9)
Requires-Dist: rapidfuzz (>=3.11.0,<4.0.0)
Requires-Dist: rouge-score (>=0.1.2,<0.2.0)
Requires-Dist: sacrebleu (>=2.5.1,<3.0.0)
